marlin_brahma/__init__.py
marlin_brahma/bots/__init__.py
marlin_brahma/bots/bot_root.py
marlin_brahma/dna/__init__.py
marlin_brahma/dna/vixen_dna.py
marlin_brahma/evo/__init__.py
marlin_brahma/evo/brahma_evo.py
marlin_brahma/fitness/__init__.py
marlin_brahma/fitness/performance.py
marlin_brahma/game/__init__.py
marlin_brahma/game/game_play.py
marlin_brahma/genes/__init__.py
marlin_brahma/genes/gene_root.py
marlin_brahma/genome/__init__.py
marlin_brahma/genome/vixen_genome.py
marlin_brahma/transcription/__init__.py
marlin_brahma/transcription/transcription.py
marlin_brahma/world/__init__.py
marlin_brahma/world/population.py
marlin_brahma-5.0.5.dist-info/METADATA
marlin_brahma-5.0.5.dist-info/WHEEL
marlin_brahma-5.0.5.dist-info/top_level.txt
marlin_brahma-5.0.5.dist-info/RECORD
