Metadata-Version: 2.4
Name: marlin_brahma
Version: 5.0.5
Summary: MARLIN Learn | GA Framework
Author: Rahul Tandon
Author-email: rahul@vixenintelligence.com
Classifier: Programming Language :: Python :: 3
Classifier: License :: OSI Approved :: MIT License
Classifier: Operating System :: OS Independent
Requires-Python: >=3.7
Dynamic: author
Dynamic: author-email
Dynamic: classifier
Dynamic: description
Dynamic: description-content-type
Dynamic: requires-python
Dynamic: summary
